{
  "archSrc": {
    "aarch64-darwin": {
      "sha256": "b0d65e1f4b4ed8c69c1fcd0e30cbd96a078347c7133b24c74ca99d26f03ac4a0",
      "url": "https://releases.hashicorp.com/terraform-provider-hcp/0.84.1/terraform-provider-hcp_0.84.1_darwin_arm64.zip"
    },
    "aarch64-linux": {
      "sha256": "c90976f1ae16bd0ee777ede7535868a7a04ae36a1ee44d41b694ce51566e2904",
      "url": "https://releases.hashicorp.com/terraform-provider-hcp/0.84.1/terraform-provider-hcp_0.84.1_linux_arm64.zip"
    },
    "i686-linux": {
      "sha256": "601c458537e3cfb69fe568e2d7a43eec8de6d569f03443731c738ee8e79dcc6b",
      "url": "https://releases.hashicorp.com/terraform-provider-hcp/0.84.1/terraform-provider-hcp_0.84.1_linux_386.zip"
    },
    "x86_64-darwin": {
      "sha256": "9682c4fe57e8428c3278233bfd6fda54ab20b4755d57adcb2cf77eaa532ab103",
      "url": "https://releases.hashicorp.com/terraform-provider-hcp/0.84.1/terraform-provider-hcp_0.84.1_darwin_amd64.zip"
    },
    "x86_64-linux": {
      "sha256": "1f1e55276364e570f394a602cc849ce38785c31a132c8ad4fa787f37feffbcad",
      "url": "https://releases.hashicorp.com/terraform-provider-hcp/0.84.1/terraform-provider-hcp_0.84.1_linux_amd64.zip"
    }
  },
  "owner": "hashicorp",
  "repo": "hcp",
  "version": "0.84.1"
}
