{
  "archSrc": {
    "aarch64-darwin": {
      "sha256": "1d88ea3af09dcf91ad0aaa0d3978ca8dcb49dc866c8615202b738d73395af6b5",
      "url": "https://releases.hashicorp.com/terraform-provider-null/3.2.0/terraform-provider-null_3.2.0_darwin_arm64.zip"
    },
    "aarch64-linux": {
      "sha256": "fe102389facd09776502327352be99becc1ac09e80bc287db84a268172be641f",
      "url": "https://releases.hashicorp.com/terraform-provider-null/3.2.0/terraform-provider-null_3.2.0_linux_arm64.zip"
    },
    "i686-linux": {
      "sha256": "3844db77bfac2aca43aaa46f3f698c8e5320a47e838ee1318408663449547e7e",
      "url": "https://releases.hashicorp.com/terraform-provider-null/3.2.0/terraform-provider-null_3.2.0_linux_386.zip"
    },
    "x86_64-darwin": {
      "sha256": "99ddc34ad13e04e9c3477f5422fbec20fc13395ff940720c287bfa5c546d2fbc",
      "url": "https://releases.hashicorp.com/terraform-provider-null/3.2.0/terraform-provider-null_3.2.0_darwin_amd64.zip"
    },
    "x86_64-linux": {
      "sha256": "b546666da4b4b60c0eec23faab7f94dc900e48f66b5436fc1ac0b87c6709ef04",
      "url": "https://releases.hashicorp.com/terraform-provider-null/3.2.0/terraform-provider-null_3.2.0_linux_amd64.zip"
    }
  },
  "owner": "hashicorp",
  "repo": "null",
  "version": "3.2.0"
}
