{
  "archSrc": {
    "aarch64-darwin": {
      "sha256": "142e262fbb162c8a86493cfab4aadaf96a8572f1a3a6be444d465a4aee377dba",
      "url": "https://releases.hashicorp.com/terraform-provider-aws/4.64.0/terraform-provider-aws_4.64.0_darwin_arm64.zip"
    },
    "aarch64-linux": {
      "sha256": "df513941e6979f557edcac28d84bd91af9786104b0deba45b3b259a5ad215897",
      "url": "https://releases.hashicorp.com/terraform-provider-aws/4.64.0/terraform-provider-aws_4.64.0_linux_arm64.zip"
    },
    "i686-linux": {
      "sha256": "7fc9581b530ebf28fda80c62c20c6fbbb936a878c24872349eb107b7f198e64c",
      "url": "https://releases.hashicorp.com/terraform-provider-aws/4.64.0/terraform-provider-aws_4.64.0_linux_386.zip"
    },
    "x86_64-darwin": {
      "sha256": "9d0a45cd4a031d19ee14c0a15f25df6359dcd342ccf4e2ee4751b3ee496edb57",
      "url": "https://releases.hashicorp.com/terraform-provider-aws/4.64.0/terraform-provider-aws_4.64.0_darwin_amd64.zip"
    },
    "x86_64-linux": {
      "sha256": "9c62bc4a9034a6caf15b8863da6f5a621b947d5fca161b4bd2f2e8e78eec8e3b",
      "url": "https://releases.hashicorp.com/terraform-provider-aws/4.64.0/terraform-provider-aws_4.64.0_linux_amd64.zip"
    }
  },
  "owner": "hashicorp",
  "repo": "aws",
  "version": "4.64.0"
}
