{
  "archSrc": {
    "aarch64-darwin": {
      "sha256": "212f833a4e6d020840672f6f88273d62a564f44acb0c857b5961cdb3bbc14c90",
      "url": "https://releases.hashicorp.com/terraform-provider-http/3.5.0/terraform-provider-http_3.5.0_darwin_arm64.zip"
    },
    "aarch64-linux": {
      "sha256": "672083810d4185076c81b16ad13d1224b9e6ea7f4850951d2ab8d30fa6e41f08",
      "url": "https://releases.hashicorp.com/terraform-provider-http/3.5.0/terraform-provider-http_3.5.0_linux_arm64.zip"
    },
    "i686-linux": {
      "sha256": "157866f700470207561f6d032d344916b82268ecd0cf8174fb11c0674c8d0736",
      "url": "https://releases.hashicorp.com/terraform-provider-http/3.5.0/terraform-provider-http_3.5.0_linux_386.zip"
    },
    "x86_64-darwin": {
      "sha256": "2c8034bc039fffaa1d4965ca02a8c6d57301e5fa9fff4773e684b46e3f78e76a",
      "url": "https://releases.hashicorp.com/terraform-provider-http/3.5.0/terraform-provider-http_3.5.0_darwin_amd64.zip"
    },
    "x86_64-linux": {
      "sha256": "a9ea5096ab91aab260b22e4251c05f08dad2ed77e43e5e4fadcdfd87f2c78926",
      "url": "https://releases.hashicorp.com/terraform-provider-http/3.5.0/terraform-provider-http_3.5.0_linux_amd64.zip"
    }
  },
  "owner": "hashicorp",
  "repo": "http",
  "version": "3.5.0"
}
