{
  "archSrc": {
    "aarch64-darwin": {
      "sha256": "0e1a94d823ec33d37434b099b215e519372029044dc52d39228d082d6833e878",
      "url": "https://releases.hashicorp.com/terraform-provider-awscc/0.66.0/terraform-provider-awscc_0.66.0_darwin_arm64.zip"
    },
    "aarch64-linux": {
      "sha256": "0eedc1c215d0ecda1a59f1867503a4d07e5437e660590de2e7cc615f62a3b837",
      "url": "https://releases.hashicorp.com/terraform-provider-awscc/0.66.0/terraform-provider-awscc_0.66.0_linux_arm64.zip"
    },
    "i686-linux": {
      "sha256": "55098c03e4709e529f6762ef245adfd5270057ca68df58354ec20f8c61781f4b",
      "url": "https://releases.hashicorp.com/terraform-provider-awscc/0.66.0/terraform-provider-awscc_0.66.0_linux_386.zip"
    },
    "x86_64-darwin": {
      "sha256": "1e12188fc22f3e58564cf83d41da02692196f0b640535b0724dacc645ae686de",
      "url": "https://releases.hashicorp.com/terraform-provider-awscc/0.66.0/terraform-provider-awscc_0.66.0_darwin_amd64.zip"
    },
    "x86_64-linux": {
      "sha256": "e8eb0c57e58529b1d03d525a9d57eaa0d504c2a174786c02144757352f397157",
      "url": "https://releases.hashicorp.com/terraform-provider-awscc/0.66.0/terraform-provider-awscc_0.66.0_linux_amd64.zip"
    }
  },
  "owner": "hashicorp",
  "repo": "awscc",
  "version": "0.66.0"
}
