{
  "archSrc": {
    "aarch64-darwin": {
      "sha256": "993fa57d502a7e95e3b03b172a8bcfc3b72bc93c2c49eb0ded8bf98d37e0e7fc",
      "url": "https://releases.hashicorp.com/terraform-provider-google/4.82.0/terraform-provider-google_4.82.0_darwin_arm64.zip"
    },
    "aarch64-linux": {
      "sha256": "448d1bb13f7f3a2eff4de601049fe5fd877f7c875b65bec5f88ebfafdfcde3e7",
      "url": "https://releases.hashicorp.com/terraform-provider-google/4.82.0/terraform-provider-google_4.82.0_linux_arm64.zip"
    },
    "i686-linux": {
      "sha256": "9fe645c4a42f826c849f209de4d71ef5f374ffa3c87e4a133e645da7224299b8",
      "url": "https://releases.hashicorp.com/terraform-provider-google/4.82.0/terraform-provider-google_4.82.0_linux_386.zip"
    },
    "x86_64-darwin": {
      "sha256": "c8512ee2087cccc09223f8e350509cb6fe53465c8a7b47d2a3c05c09262f16a1",
      "url": "https://releases.hashicorp.com/terraform-provider-google/4.82.0/terraform-provider-google_4.82.0_darwin_amd64.zip"
    },
    "x86_64-linux": {
      "sha256": "fe7e47546562b69a51d3706b12a9aa3b5fd478b18ba012980b8613dd12975d48",
      "url": "https://releases.hashicorp.com/terraform-provider-google/4.82.0/terraform-provider-google_4.82.0_linux_amd64.zip"
    }
  },
  "owner": "hashicorp",
  "repo": "google",
  "version": "4.82.0"
}
